[{"camp_id":1,"day":1,"id":1001,"temperature_weight_warm":100,"time_slot":3,"weather_weight_sunny":100,"wind_weight_nowind":100},{"camp_id":1,"day":1,"id":1002,"temperature_weight_warm":100,"time_slot":4,"weather_weight_sunny":100,"wind_weight_nowind":100},{"camp_id":1,"day":1,"id":1003,"temperature_weight_cool":100,"time_slot":5,"weather_weight_sunny":100,"wind_weight_nowind":100},{"camp_id":2,"day":1,"id":2001,"temperature_weight_warm":100,"time_slot":3,"weather_weight_sunny":100,"wind_weight_nowind":100},{"camp_id":3,"day":1,"id":3001,"temperature_weight_warm":100,"time_slot":3,"weather_weight_sunny":100,"wind_weight_nowind":100},{"camp_id":4,"day":1,"id":4001,"temperature_weight_warm":100,"time_slot":3,"weather_weight_sunny":100,"wind_weight_nowind":100},{"camp_id":5,"day":1,"id":5001,"temperature_weight_warm":100,"time_slot":3,"weather_weight_sunny":100,"wind_weight_nowind":100},{"camp_id":6,"day":1,"id":6001,"temperature_weight_warm":100,"time_slot":3,"weather_weight_sunny":100,"wind_weight_nowind":100},{"camp_id":7,"day":1,"id":7001,"temperature_weight_warm":100,"time_slot":3,"weather_weight_sunny":100,"wind_weight_nowind":100},{"camp_id":1000,"day":1,"id":100001,"temperature_weight_cool":100,"time_slot":3,"weather_weight_sunny":100,"wind_weight_nowind":100},{"camp_id":1011,"day":1,"id":101101,"temperature_weight_cool":100,"time_slot":3,"weather_weight_sunny":100,"wind_weight_nowind":100},{"camp_id":1011,"day":1,"id":101102,"temperature_weight_cool":100,"time_slot":4,"weather_weight_sunny":100,"wind_weight_nowind":100},{"camp_id":1011,"day":1,"id":101103,"temperature_weight_cool":100,"time_slot":5,"weather_weight_sunny":100,"wind_weight_nowind":100},{"camp_id":1011,"day":2,"id":101104,"temperature_weight_cool":100,"time_slot":2,"weather_weight_sunny":100,"wind_weight_nowind":100},{"camp_id":1021,"day":1,"id":102101,"temperature_weight_cool":100,"time_slot":3,"weather_weight_sunny":100,"wind_weight_nowind":100},{"camp_id":1021,"day":1,"id":102102,"temperature_weight_cool":100,"time_slot":4,"weather_weight_sunny":100,"wind_weight_nowind":100},{"camp_id":1021,"day":1,"id":102103,"temperature_weight_cool":100,"time_slot":5,"weather_weight_sunny":100,"wind_weight_nowind":100},{"camp_id":1021,"day":2,"id":102104,"temperature_weight_cool":100,"time_slot":2,"weather_weight_sunny":100,"wind_weight_nowind":100},{"camp_id":1031,"day":1,"id":103101,"temperature_weight_cool":100,"time_slot":3,"weather_weight_sunny":100,"wind_weight_nowind":100},{"camp_id":1031,"day":1,"id":103102,"temperature_weight_cool":100,"time_slot":4,"weather_weight_sunny":100,"wind_weight_nowind":100},{"camp_id":1031,"day":1,"id":103103,"temperature_weight_cool":100,"time_slot":5,"weather_weight_sunny":100,"wind_weight_nowind":100},{"camp_id":1031,"day":2,"id":103104,"temperature_weight_cool":100,"time_slot":2,"weather_weight_sunny":100,"wind_weight_nowind":100},{"camp_id":1041,"day":1,"id":104101,"temperature_weight_cool":100,"time_slot":3,"weather_weight_sunny":100,"wind_weight_nowind":100},{"camp_id":1041,"day":1,"id":104102,"temperature_weight_cool":100,"time_slot":4,"weather_weight_sunny":100,"wind_weight_nowind":100},{"camp_id":1041,"day":1,"id":104103,"temperature_weight_cool":100,"time_slot":5,"weather_weight_sunny":100,"wind_weight_nowind":100},{"camp_id":1041,"day":2,"id":104104,"temperature_weight_cool":100,"time_slot":2,"weather_weight_sunny":100,"wind_weight_nowind":100},{"camp_id":1051,"day":1,"id":105101,"temperature_weight_hot":100,"time_slot":3,"weather_weight_sunny":100,"wind_weight_nowind":100},{"camp_id":1051,"day":1,"id":105102,"temperature_weight_hot":100,"time_slot":4,"weather_weight_sunny":100,"wind_weight_nowind":100},{"camp_id":1061,"day":1,"id":106101,"temperature_weight_hot":100,"time_slot":3,"weather_weight_sunny":100,"wind_weight_nowind":100},{"camp_id":1061,"day":1,"id":106102,"temperature_weight_hot":100,"time_slot":4,"weather_weight_sunny":100,"wind_weight_nowind":100},{"camp_id":1071,"day":1,"id":107101,"temperature_weight_cool":100,"time_slot":3,"weather_weight_sunny":100,"wind_weight_nowind":100},{"camp_id":1071,"day":1,"id":107102,"temperature_weight_cool":100,"time_slot":4,"weather_weight_sunny":100,"wind_weight_nowind":100},{"camp_id":1081,"day":1,"id":108101,"temperature_weight_cool":100,"time_slot":3,"weather_weight_sunny":100,"wind_weight_nowind":100},{"camp_id":1081,"day":1,"id":108102,"temperature_weight_cool":100,"time_slot":4,"weather_weight_sunny":100,"wind_weight_nowind":100},{"camp_id":1091,"day":1,"id":109101,"temperature_weight_cool":100,"time_slot":3,"weather_weight_sunny":100,"wind_weight_nowind":100},{"camp_id":1091,"day":1,"id":109102,"temperature_weight_cool":100,"time_slot":4,"weather_weight_sunny":100,"wind_weight_nowind":100},{"camp_id":1101,"day":1,"id":110101,"temperature_weight_cool":100,"time_slot":3,"weather_weight_sunny":100,"wind_weight_nowind":100},{"camp_id":1101,"day":1,"id":110102,"temperature_weight_cool":100,"time_slot":4,"weather_weight_sunny":100,"wind_weight_nowind":100}]