[{"challenge_id":210006,"id":1,"level_guild_require":1,"reward_id":1910210006},{"challenge_id":210007,"id":2,"level_guild_require":1,"reward_id":1910210007},{"challenge_id":210008,"id":3,"level_guild_require":1,"reward_id":1910210008},{"challenge_id":210009,"id":4,"level_guild_require":1,"reward_id":1910210009},{"challenge_id":210010,"id":5,"level_guild_require":1,"reward_id":1910210010},{"challenge_id":210011,"id":6,"level_guild_require":1,"reward_id":1910210011},{"challenge_id":210012,"id":7,"level_guild_require":1,"reward_id":1910210012},{"challenge_id":210013,"id":8,"level_guild_require":1,"reward_id":1910210013},{"challenge_id":210014,"id":9,"level_guild_require":11,"reward_id":1910210014},{"challenge_id":210015,"id":10,"level_guild_require":11,"reward_id":1910210015},{"challenge_id":210016,"id":11,"level_guild_require":11,"reward_id":1910210016},{"challenge_id":210017,"id":12,"level_guild_require":11,"reward_id":1910210017},{"challenge_id":210018,"id":13,"level_guild_require":21,"reward_id":1910210018},{"challenge_id":210019,"id":14,"level_guild_require":21,"reward_id":1910210019},{"challenge_id":210020,"id":15,"level_guild_require":31,"reward_id":1910210020},{"challenge_id":210021,"id":16,"level_guild_require":31,"reward_id":1910210021},{"challenge_id":210022,"id":17,"level_guild_require":41,"reward_id":1910210022},{"challenge_id":210023,"id":18,"level_guild_require":41,"reward_id":1910210023},{"challenge_id":210024,"id":19,"level_guild_require":51,"reward_id":1910210024},{"challenge_id":210025,"id":20,"level_guild_require":51,"reward_id":1910210025},{"challenge_id":210026,"id":21,"level_guild_require":61,"reward_id":1910210026},{"challenge_id":210027,"id":22,"level_guild_require":61,"reward_id":1910210027},{"challenge_id":210028,"id":23,"level_guild_require":71,"reward_id":1910210028},{"challenge_id":210029,"id":24,"level_guild_require":71,"reward_id":1910210029},{"challenge_id":210030,"id":35,"level_guild_require":1,"reward_id":1910210030},{"challenge_id":210031,"id":36,"level_guild_require":1,"reward_id":1910210031},{"challenge_id":210032,"id":37,"level_guild_require":1,"reward_id":1910210032},{"challenge_id":210033,"id":38,"level_guild_require":1,"reward_id":1910210033}]