[{"additional_time":7,"bonus_treasure":1,"difficulty":2,"id":90101,"limit_time":60,"scroll_step":5,"scroll_time":15,"treasure_bronze_weight":70,"treasure_gold_weight":10,"treasure_silver_weight":50},{"additional_time":7,"bonus_treasure":1,"difficulty":2,"id":90102,"limit_time":60,"scroll_step":5,"scroll_time":15,"treasure_bronze_weight":70,"treasure_gold_weight":10,"treasure_silver_weight":20},{"additional_time":7,"bonus_treasure":1,"difficulty":2,"id":90103,"limit_time":60,"scroll_step":5,"scroll_time":15,"treasure_bronze_weight":70,"treasure_gold_weight":10,"treasure_silver_weight":20},{"additional_time":7,"bonus_treasure":1,"difficulty":2,"id":90104,"limit_time":60,"scroll_step":5,"scroll_time":15,"treasure_bronze_weight":70,"treasure_gold_weight":10,"treasure_silver_weight":20},{"additional_time":7,"bonus_treasure":1,"difficulty":2,"id":90105,"limit_time":60,"scroll_step":5,"scroll_time":15,"treasure_bronze_weight":70,"treasure_gold_weight":10,"treasure_silver_weight":20}]