[{"feature_id":702,"id":70201,"lower":1,"reward_id":205702001,"upper":1},{"feature_id":702,"id":70202,"lower":2,"reward_id":205702002,"upper":2},{"feature_id":702,"id":70203,"lower":3,"reward_id":205702003,"upper":3},{"feature_id":702,"id":70204,"lower":5,"reward_id":205702004,"upper":4},{"feature_id":702,"id":70205,"lower":10,"reward_id":205702005,"upper":6},{"feature_id":702,"id":70206,"lower":50,"reward_id":205702006,"upper":11},{"feature_id":702,"id":70207,"lower":100,"reward_id":205702007,"upper":51},{"feature_id":702,"id":70208,"lower":500,"reward_id":205702008,"upper":101},{"feature_id":702,"id":70209,"lower":1000,"reward_id":205702009,"upper":501},{"feature_id":702,"id":70210,"lower":3000,"reward_id":205702010,"upper":1001},{"feature_id":702,"id":70211,"lower":5000,"reward_id":205702011,"upper":3001},{"feature_id":702,"id":70212,"lower":10000,"reward_id":205702012,"upper":5001},{"feature_id":702,"id":70213,"lower":30000,"reward_id":205702013,"upper":10001},{"feature_id":702,"id":70214,"lower":50000,"reward_id":205702014,"upper":30001},{"feature_id":702,"id":70215,"lower":100000,"reward_id":205702015,"upper":50001},{"feature_id":702,"id":70216,"lower":1000000,"reward_id":205702016,"upper":100001},{"feature_id":703,"id":70301,"lower":1,"reward_id":205703001,"upper":1},{"feature_id":703,"id":70302,"lower":2,"reward_id":205703002,"upper":2},{"feature_id":703,"id":70303,"lower":3,"reward_id":205703003,"upper":3},{"feature_id":703,"id":70304,"lower":5,"reward_id":205703004,"upper":4},{"feature_id":703,"id":70305,"lower":10,"reward_id":205703005,"upper":6},{"feature_id":703,"id":70306,"lower":50,"reward_id":205703006,"upper":11},{"feature_id":703,"id":70307,"lower":100,"reward_id":205703007,"upper":51},{"feature_id":703,"id":70308,"lower":500,"reward_id":205703008,"upper":101},{"feature_id":703,"id":70309,"lower":1000,"reward_id":205703009,"upper":501},{"feature_id":703,"id":70310,"lower":3000,"reward_id":205703010,"upper":1001},{"feature_id":703,"id":70311,"lower":5000,"reward_id":205703011,"upper":3001},{"feature_id":703,"id":70312,"lower":10000,"reward_id":205703012,"upper":5001},{"feature_id":703,"id":70313,"lower":30000,"reward_id":205703013,"upper":10001},{"feature_id":703,"id":70314,"lower":50000,"reward_id":205703014,"upper":30001},{"feature_id":703,"id":70315,"lower":100000,"reward_id":205703015,"upper":50001},{"feature_id":703,"id":70316,"lower":1000000,"reward_id":205703016,"upper":100001},{"feature_id":704,"id":70401,"lower":1,"reward_id":205704001,"upper":1},{"feature_id":704,"id":70402,"lower":2,"reward_id":205704002,"upper":2},{"feature_id":704,"id":70403,"lower":3,"reward_id":205704003,"upper":3},{"feature_id":704,"id":70404,"lower":5,"reward_id":205704004,"upper":4},{"feature_id":704,"id":70405,"lower":10,"reward_id":205704005,"upper":6},{"feature_id":704,"id":70406,"lower":50,"reward_id":205704006,"upper":11},{"feature_id":704,"id":70407,"lower":100,"reward_id":205704007,"upper":51},{"feature_id":704,"id":70408,"lower":500,"reward_id":205704008,"upper":101},{"feature_id":704,"id":70409,"lower":1000,"reward_id":205704009,"upper":501},{"feature_id":704,"id":70410,"lower":3000,"reward_id":205704010,"upper":1001},{"feature_id":704,"id":70411,"lower":5000,"reward_id":205704011,"upper":3001},{"feature_id":704,"id":70412,"lower":10000,"reward_id":205704012,"upper":5001},{"feature_id":704,"id":70413,"lower":30000,"reward_id":205704013,"upper":10001},{"feature_id":704,"id":70414,"lower":50000,"reward_id":205704014,"upper":30001},{"feature_id":704,"id":70415,"lower":1000000,"reward_id":205704015,"upper":50001},{"feature_id":705,"id":70501,"lower":1,"reward_id":205705001,"upper":1},{"feature_id":705,"id":70502,"lower":2,"reward_id":205705002,"upper":2},{"feature_id":705,"id":70503,"lower":3,"reward_id":205705003,"upper":3},{"feature_id":705,"id":70504,"lower":5,"reward_id":205705004,"upper":4},{"feature_id":705,"id":70505,"lower":10,"reward_id":205705005,"upper":6},{"feature_id":705,"id":70506,"lower":50,"reward_id":205705006,"upper":11},{"feature_id":705,"id":70507,"lower":100,"reward_id":205705007,"upper":51},{"feature_id":705,"id":70508,"lower":500,"reward_id":205705008,"upper":101},{"feature_id":705,"id":70509,"lower":1000,"reward_id":205705009,"upper":501},{"feature_id":705,"id":70510,"lower":3000,"reward_id":205705010,"upper":1001},{"feature_id":705,"id":70511,"lower":5000,"reward_id":205705011,"upper":3001},{"feature_id":705,"id":70512,"lower":10000,"reward_id":205705012,"upper":5001},{"feature_id":705,"id":70513,"lower":30000,"reward_id":205705013,"upper":10001},{"feature_id":705,"id":70514,"lower":50000,"reward_id":205705014,"upper":30001},{"feature_id":705,"id":70515,"lower":1000000,"reward_id":205705015,"upper":50001},{"feature_id":706,"id":70601,"lower":1,"reward_id":205706001,"upper":1},{"feature_id":706,"id":70602,"lower":2,"reward_id":205706002,"upper":2},{"feature_id":706,"id":70603,"lower":3,"reward_id":205706003,"upper":3},{"feature_id":706,"id":70604,"lower":5,"reward_id":205706004,"upper":4},{"feature_id":706,"id":70605,"lower":10,"reward_id":205706005,"upper":6},{"feature_id":706,"id":70606,"lower":50,"reward_id":205706006,"upper":11},{"feature_id":706,"id":70607,"lower":100,"reward_id":205706007,"upper":51},{"feature_id":707,"id":70701,"lower":1,"reward_id":205707001,"upper":1},{"feature_id":707,"id":70702,"lower":2,"reward_id":205707002,"upper":2},{"feature_id":707,"id":70703,"lower":3,"reward_id":205707003,"upper":3},{"feature_id":707,"id":70704,"lower":5,"reward_id":205707004,"upper":4},{"feature_id":707,"id":70705,"lower":10,"reward_id":205707005,"upper":6},{"feature_id":707,"id":70706,"lower":50,"reward_id":205707006,"upper":11},{"feature_id":707,"id":70707,"lower":100,"reward_id":205707007,"upper":51},{"feature_id":707,"id":70708,"lower":500,"reward_id":205707008,"upper":101},{"feature_id":707,"id":70709,"lower":1000,"reward_id":205707009,"upper":501},{"feature_id":707,"id":70710,"lower":3000,"reward_id":205707010,"upper":1001},{"feature_id":707,"id":70711,"lower":5000,"reward_id":205707011,"upper":3001},{"feature_id":707,"id":70712,"lower":10000,"reward_id":205707012,"upper":5001},{"feature_id":707,"id":70713,"lower":30000,"reward_id":205707013,"upper":10001},{"feature_id":707,"id":70714,"lower":50000,"reward_id":205707014,"upper":30001},{"feature_id":707,"id":70715,"lower":1000000,"reward_id":205707015,"upper":50001},{"feature_id":708,"id":70801,"lower":1,"reward_id":205708001,"upper":1},{"feature_id":708,"id":70802,"lower":2,"reward_id":205708002,"upper":2},{"feature_id":708,"id":70803,"lower":3,"reward_id":205708003,"upper":3},{"feature_id":708,"id":70804,"lower":5,"reward_id":205708004,"upper":4},{"feature_id":708,"id":70805,"lower":10,"reward_id":205708005,"upper":6},{"feature_id":708,"id":70806,"lower":50,"reward_id":205708006,"upper":11},{"feature_id":708,"id":70807,"lower":100,"reward_id":205708007,"upper":51},{"feature_id":708,"id":70808,"lower":500,"reward_id":205708008,"upper":101},{"feature_id":708,"id":70809,"lower":1000,"reward_id":205708009,"upper":501},{"feature_id":708,"id":70810,"lower":3000,"reward_id":205708010,"upper":1001},{"feature_id":708,"id":70811,"lower":5000,"reward_id":205708011,"upper":3001},{"feature_id":708,"id":70812,"lower":10000,"reward_id":205708012,"upper":5001},{"feature_id":708,"id":70813,"lower":30000,"reward_id":205708013,"upper":10001},{"feature_id":708,"id":70814,"lower":50000,"reward_id":205708014,"upper":30001},{"feature_id":708,"id":70815,"lower":1000000,"reward_id":205708015,"upper":50001},{"feature_id":902,"id":90201,"lower":1,"reward_id":205902001,"upper":1},{"feature_id":902,"id":90202,"lower":2,"reward_id":205902002,"upper":2},{"feature_id":902,"id":90203,"lower":3,"reward_id":205902003,"upper":3},{"feature_id":902,"id":90204,"lower":10,"reward_id":205902004,"upper":4},{"feature_id":902,"id":90205,"lower":100,"reward_id":205902005,"upper":11},{"feature_id":902,"id":90206,"lower":1000,"reward_id":205902006,"upper":101},{"feature_id":902,"id":90207,"lower":1000000,"reward_id":205902007,"upper":1001}]